savable/__init__.py
savable/savable.py
savable-1.0.0.dist-info/LICENSE
savable-1.0.0.dist-info/METADATA
savable-1.0.0.dist-info/WHEEL
savable-1.0.0.dist-info/top_level.txt
savable-1.0.0.dist-info/RECORD
