Metadata-Version: 2.1
Name: savable
Version: 1.0.0
Summary: A Python utility for making child classes savable,
Author-email: Giacomo Tanzi <giacomo.tanzi14@gmail.com>
License: MIT License
Project-URL: Homepage, https://github.com/gtanzi/savable
Keywords: savable
Classifier: License :: OSI Approved :: MIT License
Classifier: Programming Language :: Python :: 3
Classifier: Topic :: Software Development :: Libraries :: Python Modules
Requires-Python: >=3.9
License-File: LICENSE
Provides-Extra: dev
